{"title":"AnnaMyst - Practicing my kickboxing on my nude slave.wmv","uid":11795499,"size":312439534,"categoryP":"porn","categoryS":"movies","magnet":"?xt=urn:btih:047fb5a4fe9ff571aadddaf4696610ddf08c4e28&amp;dn=AnnaMyst+-+Practicing+my+kickboxing+on+my+nude+slave.wmv&amp;tr=udp%3A%2F%2Ftracker.openbittorrent.com%3A80&amp;tr=udp%3A%2F%2Fopen.demonii.com%3A1337&amp;tr=udp%3A%2F%2Ftracker.coppersurfer.tk%3A6969&amp;tr=udp%3A%2F%2Fexodus.desync.com%3A6969","seeders":3,"leechers":0,"uploader":"merzedes","files":1,"time":1428152704,"description":"AnnaMyst - Practicing my kickboxing on my nude slave.wmv\n\n\nScreens\n &lt;a href=&quot;\nhttp://s28.postimg.org/a8d0zrkb1/Anna_Myst_Practicing_my_kickboxing_on_my_nude_sla.jpg&quot; rel=&quot;nofollow&quot; target=&quot;_NEW&quot;&gt;\nhttp://s28.postimg.org/a8d0zrkb1/Anna_Myst_Practicing_my_kickboxing_on_my_nude_sla.jpg&lt;/a&gt;\n\n\n Uploaded by Merzedes and Shallow2 \n\n 17 000 Femdom/BDSM/Fetish torrentuploads completed. Man.. feels like every 1000 goes by faster and faster ;)\n\n Just keep on leaving us the nice comments below and we are happy :)\n\n Any Questions ?? Read our FAQ!!\n\n &lt;a href=&quot;\nhttp://s16.postimg.org/rxyfm...llow2_FAQ_The_Pirate_Bay.jpg&quot; rel=&quot;nofollow&quot; target=&quot;_NEW&quot;&gt;\nhttp://s16.postimg.org/rxyfm...llow2_FAQ_The_Pirate_Bay.jpg&lt;/a&gt;\n\n Cheers :-)","torrent":{"xt":"urn:btih:047fb5a4fe9ff571aadddaf4696610ddf08c4e28","amp;dn":"AnnaMyst+-+Practicing+my+kickboxing+on+my+nude+slave.wmv","amp;tr":["udp%3A%2F%2Ftracker.openbittorrent.com%3A80","udp%3A%2F%2Fopen.demonii.com%3A1337","udp%3A%2F%2Ftracker.coppersurfer.tk%3A6969","udp%3A%2F%2Fexodus.desync.com%3A6969"],"infoHash":"047fb5a4fe9ff571aadddaf4696610ddf08c4e28","infoHashBuffer":{"type":"Buffer","data":[4,127,181,164,254,159,245,113,170,221,218,244,105,102,16,221,240,140,78,40]},"announce":[],"urlList":[]}}