{"title":"CherryPimps_15.08.19.Babe.Dillion.Fucks.LIVE.XXX.iMAGESET-YAPG","uid":12278345,"size":26094489,"categoryP":"porn","categoryS":"pictures","magnet":"?xt=urn:btih:04d4689d364ad04ab4973d9a265ee4160520b2a2&amp;dn=CherryPimps_15.08.19.Babe.Dillion.Fucks.LIVE.XXX.iMAGESET-YAPG&amp;tr=udp%3A%2F%2Ftracker.openbittorrent.com%3A80&amp;tr=udp%3A%2F%2Fopen.demonii.com%3A1337&amp;tr=udp%3A%2F%2Ftracker.coppersurfer.tk%3A6969&amp;tr=udp%3A%2F%2Fexodus.desync.com%3A6969","seeders":3,"leechers":1,"uploader":"Ctrlme","files":208,"time":1440382878,"description":"-----------------------------------------------------------\nCherryPimps.com_15.08.19.Babe.Dillion.Fucks.LIVE.XXX.iMAGESET-YAPG\n-----------------------------------------------------------\nScreenshots: &lt;a href=&quot;\nhttp://imgctrl.com/image/NeE&quot; rel=&quot;nofollow&quot; target=&quot;_NEW&quot;&gt;\nhttp://imgctrl.com/image/NeE&lt;/a&gt; &lt;a href=&quot;\nhttp://imgctrl.com/image/NeF&quot; rel=&quot;nofollow&quot; target=&quot;_NEW&quot;&gt;\nhttp://imgctrl.com/image/NeF&lt;/a&gt; &lt;a href=&quot;\nhttp://imgctrl.com/image/NeS&quot; rel=&quot;nofollow&quot; target=&quot;_NEW&quot;&gt;\nhttp://imgctrl.com/image/NeS&lt;/a&gt; &lt;a href=&quot;\nhttp://imgctrl.com/image/Nef&quot; rel=&quot;nofollow&quot; target=&quot;_NEW&quot;&gt;\nhttp://imgctrl.com/image/Nef&lt;/a&gt; &lt;a href=&quot;\nhttp://imgctrl.com/image/Neo&quot; rel=&quot;nofollow&quot; target=&quot;_NEW&quot;&gt;\nhttp://imgctrl.com/image/Neo&lt;/a&gt;\n-----------------------------------------------------------\nIf you like this torrent, please post a comment!\n\nDon't forget to seed!","torrent":{"xt":"urn:btih:04d4689d364ad04ab4973d9a265ee4160520b2a2","amp;dn":"CherryPimps_15.08.19.Babe.Dillion.Fucks.LIVE.XXX.iMAGESET-YAPG","amp;tr":["udp%3A%2F%2Ftracker.openbittorrent.com%3A80","udp%3A%2F%2Fopen.demonii.com%3A1337","udp%3A%2F%2Ftracker.coppersurfer.tk%3A6969","udp%3A%2F%2Fexodus.desync.com%3A6969"],"infoHash":"04d4689d364ad04ab4973d9a265ee4160520b2a2","infoHashBuffer":{"type":"Buffer","data":[4,212,104,157,54,74,208,74,180,151,61,154,38,94,228,22,5,32,178,162]},"announce":[],"urlList":[]}}