{"title":"Nemacki u 100 lekcija","uid":8802896,"size":123317302,"categoryP":"other","categoryS":"e_books","magnet":"?xt=urn:btih:0b2fa9cac0570ec4b59d178a841f81ad5a5c6aac&amp;dn=Nemacki+u+100+lekcija&amp;tr=udp%3A%2F%2Ftracker.openbittorrent.com%3A80&amp;tr=udp%3A%2F%2Fopen.demonii.com%3A1337&amp;tr=udp%3A%2F%2Ftracker.coppersurfer.tk%3A6969&amp;tr=udp%3A%2F%2Fexodus.desync.com%3A6969","seeders":3,"leechers":0,"uploader":"LainStain","files":-1,"time":1376252823,"description":"Dr. Alojz Straus - Nemacki u 100 lekcija\n\nOdlicna knjiga za sve koji zele da nauce nemacki jezik. Video sam da je trazena ali i nedostupna na internetu pa sam odlucio da je podelim sa svima kojima treba. I sam je koristim.\n\nEnjoy and seed!","torrent":{"xt":"urn:btih:0b2fa9cac0570ec4b59d178a841f81ad5a5c6aac","amp;dn":"Nemacki+u+100+lekcija","amp;tr":["udp%3A%2F%2Ftracker.openbittorrent.com%3A80","udp%3A%2F%2Fopen.demonii.com%3A1337","udp%3A%2F%2Ftracker.coppersurfer.tk%3A6969","udp%3A%2F%2Fexodus.desync.com%3A6969"],"infoHash":"0b2fa9cac0570ec4b59d178a841f81ad5a5c6aac","infoHashBuffer":{"type":"Buffer","data":[11,47,169,202,192,87,14,196,181,157,23,138,132,31,129,173,90,92,106,172]},"announce":[],"urlList":[]}}