{"title":"Lady-Sonia.14.10.08.Fur.Coat.And.Thigh.Boots.In.The.Woods.XXX.72","uid":11421731,"size":465155837,"categoryP":"porn","categoryS":"other","magnet":"?xt=urn:btih:11ba5c1fcf5c02471c38abd8b524fd9b517efa41&amp;dn=Lady-Sonia.14.10.08.Fur.Coat.And.Thigh.Boots.In.The.Woods.XXX.72&amp;tr=udp%3A%2F%2Ftracker.openbittorrent.com%3A80&amp;tr=udp%3A%2F%2Fopen.demonii.com%3A1337&amp;tr=udp%3A%2F%2Ftracker.coppersurfer.tk%3A6969&amp;tr=udp%3A%2F%2Fexodus.desync.com%3A6969","seeders":3,"leechers":0,"uploader":"DrarbgXXX","files":3,"time":1415627974,"description":" &lt;a href=&quot;https://rarbg.com&quot; rel=&quot;nofollow&quot; target=&quot;_NEW&quot;&gt;https://rarbg.com&lt;/a&gt;\n\nLady-Sonia.14.10.08.Fur.Coat.And.Thigh.Boots.In.The.Woods.XXX.720p.MP4-OHRLY\n-----------------------------------------\nScreens : &lt;a href=&quot;\nhttp://imgcrl.org/v/51007125205622523262/&quot; rel=&quot;nofollow&quot; target=&quot;_NEW&quot;&gt;\nhttp://imgcrl.org/v/51007125205622523262/&lt;/a&gt;\n\n-----------------------------------------\nAuto Media Info :\nVideo Format........: AVC\nCodec ID............: avc1\nLength..............: 12mn9s\nVideo...............: 1280x720 ( 25.000fps )\nBitrate.............: Variable\nAudio Format........: AAC\nCodec ID............: 40\nBit rate mode.......: Constant\nBitrate.............: 157Kbps\nChannel(s)..........: 2 channels","torrent":{"xt":"urn:btih:11ba5c1fcf5c02471c38abd8b524fd9b517efa41","amp;dn":"Lady-Sonia.14.10.08.Fur.Coat.And.Thigh.Boots.In.The.Woods.XXX.72","amp;tr":["udp%3A%2F%2Ftracker.openbittorrent.com%3A80","udp%3A%2F%2Fopen.demonii.com%3A1337","udp%3A%2F%2Ftracker.coppersurfer.tk%3A6969","udp%3A%2F%2Fexodus.desync.com%3A6969"],"infoHash":"11ba5c1fcf5c02471c38abd8b524fd9b517efa41","infoHashBuffer":{"type":"Buffer","data":[17,186,92,31,207,92,2,71,28,56,171,216,181,36,253,155,81,126,250,65]},"announce":[],"urlList":[]}}