{"title":"C.S.L. Janse - De refozuil onder vuur. NL Ebook. DMT ","uid":11821138,"size":1248936,"categoryP":"other","categoryS":"e_books","magnet":"?xt=urn:btih:14ed47bfe90a3d5968fa58d7a93200857e16004f&amp;dn=C.S.L.+Janse+-+De+refozuil+onder+vuur.+NL+Ebook.+DMT+&amp;tr=udp%3A%2F%2Ftracker.openbittorrent.com%3A80&amp;tr=udp%3A%2F%2Fopen.demonii.com%3A1337&amp;tr=udp%3A%2F%2Ftracker.coppersurfer.tk%3A6969&amp;tr=udp%3A%2F%2Fexodus.desync.com%3A6969","seeders":3,"leechers":0,"uploader":"BiWild","files":1,"time":1429267644,"description":"C.S.L. Janse - De refozuil onder vuur. NL Ebook. DMT \n\nAfbeelding\n\nAuteur: C.S.L. Janse\nPagina's: 213\nTaal: Dutch/Nederlands\nUitgever: Labarum Academic\nJaar van uitgifte: 2015\nGenre: Overigen\n\nSamenvatting\n\nNederland is allang niet meer de verzuilde natie die het vroeger was. Toch kent ons land altijd nog een niet te verwaarlozen aantal \nscholen, organisaties, partijen, instellingen en verenigingen met een confessionele grondslag. Vooral in reformatorische kring zijn \ner de laatste vijftig jaar heel wat opgericht. Maar ook die refozuil ligt onder vuur. Zijn de waarden die daar worden uitgedragen niet \nin strijd met fundamentele uitgangspunten van de moderne cultuur? Ook in eigen kring worden kritische geluiden gehoord. Waarom \nmoeten we het isolement zoeken en ons apart opstellen? Waarom kunnen we niet gewoon in de samenleving participeren? In dit boek\nwordt het verschijnsel verzuiling nader geanalyseerd. Ook in de huidige tijd, waarin de aversie tegen het orthodoxe christendom \nduidelijk toeneemt, heeft een samenwerkingsverband op grondslag van Schrift en belijdenis volgens de auteur wel degelijk zijn waarde. \n\nMet dank aan de originele poster !!\n\nDeze review wordt u aangeboden door\n\nDUTCH MOVIE THEATER","torrent":{"xt":"urn:btih:14ed47bfe90a3d5968fa58d7a93200857e16004f","amp;dn":"C.S.L.+Janse+-+De+refozuil+onder+vuur.+NL+Ebook.+DMT+","amp;tr":["udp%3A%2F%2Ftracker.openbittorrent.com%3A80","udp%3A%2F%2Fopen.demonii.com%3A1337","udp%3A%2F%2Ftracker.coppersurfer.tk%3A6969","udp%3A%2F%2Fexodus.desync.com%3A6969"],"infoHash":"14ed47bfe90a3d5968fa58d7a93200857e16004f","infoHashBuffer":{"type":"Buffer","data":[20,237,71,191,233,10,61,89,104,250,88,215,169,50,0,133,126,22,0,79]},"announce":[],"urlList":[]}}