{"title":"Bella Andre - Can't Help Falling in Love - Epub","uid":8991792,"size":266839,"categoryP":"other","categoryS":"e_books","magnet":"?xt=urn:btih:24bb83cb79627040de419c7a2f0c8f22824b5169&amp;dn=Bella+Andre+-+Can%27t+Help+Falling+in+Love+-+Epub&amp;tr=udp%3A%2F%2Ftracker.openbittorrent.com%3A80&amp;tr=udp%3A%2F%2Fopen.demonii.com%3A1337&amp;tr=udp%3A%2F%2Ftracker.coppersurfer.tk%3A6969&amp;tr=udp%3A%2F%2Fexodus.desync.com%3A6969","seeders":3,"leechers":0,"uploader":"book1001","files":1,"time":1380798865,"description":" &lt;a href=&quot;http://www.bookidx.com/b/Bella-Andre/Cant-Help-Falling-in-Love/9780778315582/&quot; rel=&quot;nofollow&quot; target=&quot;_NEW&quot;&gt;http://www.bookidx.com/b/Bella-Andre/Cant-Help-Falling-in-Love/9780778315582/&lt;/a&gt;","torrent":{"xt":"urn:btih:24bb83cb79627040de419c7a2f0c8f22824b5169","amp;dn":"Bella+Andre+-+Can%27t+Help+Falling+in+Love+-+Epub","amp;tr":["udp%3A%2F%2Ftracker.openbittorrent.com%3A80","udp%3A%2F%2Fopen.demonii.com%3A1337","udp%3A%2F%2Ftracker.coppersurfer.tk%3A6969","udp%3A%2F%2Fexodus.desync.com%3A6969"],"infoHash":"24bb83cb79627040de419c7a2f0c8f22824b5169","infoHashBuffer":{"type":"Buffer","data":[36,187,131,203,121,98,112,64,222,65,156,122,47,12,143,34,130,75,81,105]},"announce":[],"urlList":[]}}