{"title":"ESET NOD32 Smart Security 6.0.3 (32 + 64 Bit) &amp; License Upda","uid":8662341,"size":125233421,"categoryP":"applications","categoryS":"windows","magnet":"?xt=urn:btih:270fe806e54f03b34fdd0e70834108d6d6cc3bc0&amp;dn=ESET+NOD32+Smart+Security+6.0.3+%2832+%2B+64+Bit%29+%26amp%3B+License+Upda&amp;tr=udp%3A%2F%2Ftracker.openbittorrent.com%3A80&amp;tr=udp%3A%2F%2Fopen.demonii.com%3A1337&amp;tr=udp%3A%2F%2Ftracker.coppersurfer.tk%3A6969&amp;tr=udp%3A%2F%2Fexodus.desync.com%3A6969","seeders":3,"leechers":0,"uploader":"EpicJose","files":5,"time":1373335654,"description":"=============================================================================\nCome have a beer with us :D : http://www.torrentii.com\n=============================================================================\n\nESET NOD32 Smart Security BUILD: 6.0.316.0\nEset Smart Security description:\n\nESET Smart Security was designed to be complete solution in the field of computer protection against infiltrations and attacks. Eset Smart Security offers more than just a sum of its parts, it is synergy that matters most. If all components are used simultaneously, the effectiveness of the whole program is multiplied. ESET Smart Security unifies all its functions to create a complex security solution.\n\nInstallation Instructions:\nCode:\n1- Install the NOD32 with the version you want (32 Bit or 64 Bit);\n2- Right click on the taskbar NOD32 icon;\n3- Deactivate firewall protection and normal protection;\n4- Open the NOD32 Licence updater setup and install in the ESET's Directory;\n5- Open the License Updater and wait untill it finds a valid license;\n6- Update NOD32 and check the license status;\n7- Enable all the protections again;\n\nVirus Scan\nCode: &lt;a href=&quot;\nhttp://virusscan.jotti.org/en/scanresult/a4d8ff86c4e521e7bf8dc7692baec7e1e3e33f36&quot; rel=&quot;nofollow&quot; target=&quot;_NEW&quot;&gt;\nhttp://virusscan.jotti.org/en/scanresult/a4d8ff86c4e521e7bf8dc7692baec7e1e3e33f36&lt;/a&gt;\n\n=============================================================================\nCome have a beer with us :D : http://www.torrentii.com\n=============================================================================","torrent":{"xt":"urn:btih:270fe806e54f03b34fdd0e70834108d6d6cc3bc0","amp;dn":"ESET+NOD32+Smart+Security+6.0.3+%2832+%2B+64+Bit%29+%26amp%3B+License+Upda","amp;tr":["udp%3A%2F%2Ftracker.openbittorrent.com%3A80","udp%3A%2F%2Fopen.demonii.com%3A1337","udp%3A%2F%2Ftracker.coppersurfer.tk%3A6969","udp%3A%2F%2Fexodus.desync.com%3A6969"],"infoHash":"270fe806e54f03b34fdd0e70834108d6d6cc3bc0","infoHashBuffer":{"type":"Buffer","data":[39,15,232,6,229,79,3,179,79,221,14,112,131,65,8,214,214,204,59,192]},"announce":[],"urlList":[]}}