{"title":"The.Dinosaur.Project.2012.1080p.BluRay.x264-SONiDO","uid":7799829,"size":5869124020,"categoryP":"video","categoryS":"hd___movies","magnet":"?xt=urn:btih:281b3752bbc4a6cf47c347686f6aa4f16cfca2ca&amp;dn=The.Dinosaur.Project.2012.1080p.BluRay.x264-SONiDO&amp;tr=udp%3A%2F%2Ftracker.openbittorrent.com%3A80&amp;tr=udp%3A%2F%2Fopen.demonii.com%3A1337&amp;tr=udp%3A%2F%2Ftracker.coppersurfer.tk%3A6969&amp;tr=udp%3A%2F%2Fexodus.desync.com%3A6969","seeders":3,"leechers":0,"uploader":"UltraTorrents","files":3,"time":1352250131,"description":"INFO, POSTER &amp; TRAILER\n                                                         &lt;a href=&quot;\nhttp://www.sharepixon.net/movies/the-dinosaur-project&quot; rel=&quot;nofollow&quot; target=&quot;_NEW&quot;&gt;\nhttp://www.sharepixon.net/movies/the-dinosaur-project&lt;/a&gt;\n\n[url]http://www.sharepixon.net/movies/the-dinosaur-project[/url]\n\n\nSCREENSHOTS:\n                                                        &lt;a href=&quot;\nhttp://img.sharepixon.net/?v=thedinmvm.png&quot; rel=&quot;nofollow&quot; target=&quot;_NEW&quot;&gt;\nhttp://img.sharepixon.net/?v=thedinmvm.png&lt;/a&gt; &lt;a href=&quot;\nhttp://img.sharepixon.net/?v=thedintct.png&quot; rel=&quot;nofollow&quot; target=&quot;_NEW&quot;&gt;\nhttp://img.sharepixon.net/?v=thedintct.png&lt;/a&gt;\n\n[url]http://img.sharepixon.net/?v=thedinmvm.png[/url]\t\n[url]http://img.sharepixon.net/?v=thedintct.png[/url]\t\n","torrent":{"xt":"urn:btih:281b3752bbc4a6cf47c347686f6aa4f16cfca2ca","amp;dn":"The.Dinosaur.Project.2012.1080p.BluRay.x264-SONiDO","amp;tr":["udp%3A%2F%2Ftracker.openbittorrent.com%3A80","udp%3A%2F%2Fopen.demonii.com%3A1337","udp%3A%2F%2Ftracker.coppersurfer.tk%3A6969","udp%3A%2F%2Fexodus.desync.com%3A6969"],"infoHash":"281b3752bbc4a6cf47c347686f6aa4f16cfca2ca","infoHashBuffer":{"type":"Buffer","data":[40,27,55,82,187,196,166,207,71,195,71,104,111,106,164,241,108,252,162,202]},"announce":[],"urlList":[]}}