{"title":"Ewa Sonnet - I R&amp;B, polish sexy singer very hot","uid":4168249,"size":51996432,"categoryP":"video","categoryS":"music_videos","magnet":"?xt=urn:btih:2e114c1ea77386643e5cedaf39650ff3124fe589&amp;dn=Ewa+Sonnet+-+I+R%26B%2C+polish+sexy+singer+very+hot&amp;tr=udp%3A%2F%2Ftracker.openbittorrent.com%3A80&amp;tr=udp%3A%2F%2Fopen.demonii.com%3A1337&amp;tr=udp%3A%2F%2Ftracker.coppersurfer.tk%3A6969&amp;tr=udp%3A%2F%2Fexodus.desync.com%3A6969","seeders":3,"leechers":0,"uploader":"oracenelson","files":1,"time":1209724519,"description":"FOR COMPLETE DESCRIPTION AND PICTURES,SEE:\n &lt;a href=&quot;\nhttp://forum.tntvillage.scambioetico.org/tntforum/index.php?showtopic=124659&quot; rel=&quot;nofollow&quot; target=&quot;_NEW&quot;&gt;\nhttp://forum.tntvillage.scambioetico.org/tntforum/index.php?showtopic=124659&lt;/a&gt;\n\n\n\n\nGeneral #0\nComplete name                : Ewa Sonnet - I R&amp;B.avi\nFormat                       : AVI\nFormat/Info                  : Audio Video Interleave\nFormat/Family                : RIFF\nFile size                    : 49.6 MiB\nPlayTime                     : 3mn 1s\nBit rate                     : 2291 Kbps\nStreamSize                   : 224 KiB\nWriting library              : VirtualDub-MPEG2 build 23889/release\n\nVideo #0\nCodec                        : XviD\nCodec/Family                 : MPEG-4V\nCodec/Info                   : XviD project\nCodec profile                : Streaming Video Profile/Level 1\nCodec settings, Packet bitst : Yes\nCodec settings, BVOP         : Yes\nCodec settings, QPel         : No\nCodec settings, GMC          : 0\nCodec settings, Matrix       : Default\nPlayTime                     : 3mn 1s\nBit rate                     : 2089 Kbps\nWidth                        : 720 pixels\nHeight                       : 420 pixels\nDisplay Aspect ratio         : 16/9\nFrame rate                   : 25.000 fps\nResolution                   : 8 bits\nChroma                       : 4:2:0\nInterlacement                : Progressive\nBits/(Pixel*Frame)           : 0.276\nStreamSize                   : 45.2 MiB\nWriting library              : XviD 1.2.-127(dev)\nWriting library/Date         : UTC2006-11-01\n\nAudio #0\nCodec                        : MPEG-1 Audio layer 3\nCodec profile                : Joint stereo\nPlayTime                     : 3mn 1s\nBit rate mode                : CBR\nBit rate                     : 192 Kbps\nChannel(s)                   : 2 channels\nSampling rate                : 48 KHz\nResolution                   : 16 bits\nStreamSize                   : 4.16 MiB","torrent":{"xt":"urn:btih:2e114c1ea77386643e5cedaf39650ff3124fe589","amp;dn":"Ewa+Sonnet+-+I+R%26B%2C+polish+sexy+singer+very+hot","amp;tr":["udp%3A%2F%2Ftracker.openbittorrent.com%3A80","udp%3A%2F%2Fopen.demonii.com%3A1337","udp%3A%2F%2Ftracker.coppersurfer.tk%3A6969","udp%3A%2F%2Fexodus.desync.com%3A6969"],"infoHash":"2e114c1ea77386643e5cedaf39650ff3124fe589","infoHashBuffer":{"type":"Buffer","data":[46,17,76,30,167,115,134,100,62,92,237,175,57,101,15,243,18,79,229,137]},"announce":[],"urlList":[]}}