{"title":"OM","uid":7146269,"size":339192376,"categoryP":"audio","categoryS":"music","magnet":"?xt=urn:btih:330676b90e5ccd4008bc8db5258ef43120413bde&amp;dn=OM&amp;tr=udp%3A%2F%2Ftracker.openbittorrent.com%3A80&amp;tr=udp%3A%2F%2Fopen.demonii.com%3A1337&amp;tr=udp%3A%2F%2Ftracker.coppersurfer.tk%3A6969&amp;tr=udp%3A%2F%2Fexodus.desync.com%3A6969","seeders":3,"leechers":0,"uploader":"skygoat","files":20,"time":1333154497,"description":"Variations on a Theme:\n\n1. On the Mountain at Dawn\n2. Kapila's Theme\n3. Annapurna\n\nConference of the Birds:\n\n1. At Giza\n2. Flight of the Eagle\n\nGod Is Good:\n\n1. Thebes\n2. Meditation is the Practice of Death\n3. Cremation Ghat I\n4. Cremation Ghat II\n\nPilgrimage:\n\n1. Pilgrimage\n2. Unitive Knowledge of the Godhead\n3. Bhima's Theme\n4. Pilgrimage (Reprise)\n\nGebel Barkal:\n\n1. Gebel Barkal\n2. (Version)","torrent":{"xt":"urn:btih:330676b90e5ccd4008bc8db5258ef43120413bde","amp;dn":"OM","amp;tr":["udp%3A%2F%2Ftracker.openbittorrent.com%3A80","udp%3A%2F%2Fopen.demonii.com%3A1337","udp%3A%2F%2Ftracker.coppersurfer.tk%3A6969","udp%3A%2F%2Fexodus.desync.com%3A6969"],"infoHash":"330676b90e5ccd4008bc8db5258ef43120413bde","infoHashBuffer":{"type":"Buffer","data":[51,6,118,185,14,92,205,64,8,188,141,181,37,142,244,49,32,65,59,222]},"announce":[],"urlList":[]}}