{"title":"The X Factor AU Live Final Rd Sun 19 Oct S06E33","uid":11245897,"size":1644550121,"categoryP":"video","categoryS":"hd___tv_shows","magnet":"?xt=urn:btih:33e8c4f5212ac29f2e483a4cc29d21abf5abd16e&amp;dn=The+X+Factor+AU+Live+Final+Rd+Sun+19+Oct+S06E33&amp;tr=udp%3A%2F%2Ftracker.openbittorrent.com%3A80&amp;tr=udp%3A%2F%2Fopen.demonii.com%3A1337&amp;tr=udp%3A%2F%2Ftracker.coppersurfer.tk%3A6969&amp;tr=udp%3A%2F%2Fexodus.desync.com%3A6969","seeders":3,"leechers":0,"uploader":"c9j10","files":1,"time":1413738798,"description":"Name:The X Factor AU Live Final Rd Part 1 of 2 Sun 19 Oct S06E33.mp4\n\n\nDuration:01:39:34\nResolution:1024 * 576\nBit Rate:2005 kbps\nFrame Rate:25\nSample Rate:48000 kbps\nBit Rate:192 kbps\nChannel:6","torrent":{"xt":"urn:btih:33e8c4f5212ac29f2e483a4cc29d21abf5abd16e","amp;dn":"The+X+Factor+AU+Live+Final+Rd+Sun+19+Oct+S06E33","amp;tr":["udp%3A%2F%2Ftracker.openbittorrent.com%3A80","udp%3A%2F%2Fopen.demonii.com%3A1337","udp%3A%2F%2Ftracker.coppersurfer.tk%3A6969","udp%3A%2F%2Fexodus.desync.com%3A6969"],"infoHash":"33e8c4f5212ac29f2e483a4cc29d21abf5abd16e","infoHashBuffer":{"type":"Buffer","data":[51,232,196,245,33,42,194,159,46,72,58,76,194,157,33,171,245,171,209,110]},"announce":[],"urlList":[]}}