{"title":"Wall Street Journal  July 23rd  2014 (Europe)","uid":10616131,"size":8096914,"categoryP":"other","categoryS":"e_books","magnet":"?xt=urn:btih:398dfac8d9978c59523ccc332eb9a020e02fb32b&amp;dn=Wall+Street+Journal++July+23rd++2014+%28Europe%29&amp;tr=udp%3A%2F%2Ftracker.openbittorrent.com%3A80&amp;tr=udp%3A%2F%2Fopen.demonii.com%3A1337&amp;tr=udp%3A%2F%2Ftracker.coppersurfer.tk%3A6969&amp;tr=udp%3A%2F%2Fexodus.desync.com%3A6969","seeders":3,"leechers":0,"uploader":"sidmal","files":-1,"time":1406115905,"description":"\nThe Wall Street Journal (Europe) July 23 2014\n 7,7 MB | PDF | Retail | 28 Pages | english\n\n","torrent":{"xt":"urn:btih:398dfac8d9978c59523ccc332eb9a020e02fb32b","amp;dn":"Wall+Street+Journal++July+23rd++2014+%28Europe%29","amp;tr":["udp%3A%2F%2Ftracker.openbittorrent.com%3A80","udp%3A%2F%2Fopen.demonii.com%3A1337","udp%3A%2F%2Ftracker.coppersurfer.tk%3A6969","udp%3A%2F%2Fexodus.desync.com%3A6969"],"infoHash":"398dfac8d9978c59523ccc332eb9a020e02fb32b","infoHashBuffer":{"type":"Buffer","data":[57,141,250,200,217,151,140,89,82,60,204,51,46,185,160,32,224,47,179,43]},"announce":[],"urlList":[]}}