{"title":"Foolproof (2003) | HDTVRip | 720p | Hindi | Eng | BHATTI87","uid":7745369,"size":1081784399,"categoryP":"video","categoryS":"hd___movies","magnet":"?xt=urn:btih:469a5f0f9099d234bd01672d1fcde60267ae1643&amp;dn=Foolproof+%282003%29+%7C+HDTVRip+%7C+720p+%7C+Hindi+%7C+Eng+%7C+BHATTI87&amp;tr=udp%3A%2F%2Ftracker.openbittorrent.com%3A80&amp;tr=udp%3A%2F%2Fopen.demonii.com%3A1337&amp;tr=udp%3A%2F%2Ftracker.coppersurfer.tk%3A6969&amp;tr=udp%3A%2F%2Fexodus.desync.com%3A6969","seeders":3,"leechers":3,"uploader":"BHATTI87","files":19,"time":1350749105,"description":"Foolproof (2003) | HDTVRip | 720p | Hindi | Eng | BHATTI87\n\n\n &lt;a href=&quot;\nhttp://img850.imageshack.us/img850/273/coverfpe.jpg&quot; rel=&quot;nofollow&quot; target=&quot;_NEW&quot;&gt;\nhttp://img850.imageshack.us/img850/273/coverfpe.jpg&lt;/a&gt;\n\n &lt;a href=&quot;\nhttp://img221.imageshack.us/img221/9316/infofb.jpg&quot; rel=&quot;nofollow&quot; target=&quot;_NEW&quot;&gt;\nhttp://img221.imageshack.us/img221/9316/infofb.jpg&lt;/a&gt;\n\n\n &lt;a href=&quot;\nhttp://img21.imageshack.us/img21/4100/19922388.jpg&quot; rel=&quot;nofollow&quot; target=&quot;_NEW&quot;&gt;\nhttp://img21.imageshack.us/img21/4100/19922388.jpg&lt;/a&gt; &lt;a href=&quot;\nhttp://img89.imageshack.us/img89/3994/fp1b.jpg&quot; rel=&quot;nofollow&quot; target=&quot;_NEW&quot;&gt;\nhttp://img89.imageshack.us/img89/3994/fp1b.jpg&lt;/a&gt; &lt;a href=&quot;\nhttp://img202.imageshack.us/img202/5181/fp2lt.jpg&quot; rel=&quot;nofollow&quot; target=&quot;_NEW&quot;&gt;\nhttp://img202.imageshack.us/img202/5181/fp2lt.jpg&lt;/a&gt; &lt;a href=&quot;\nhttp://img707.imageshack.us/img707/7886/fp3up.jpg&quot; rel=&quot;nofollow&quot; target=&quot;_NEW&quot;&gt;\nhttp://img707.imageshack.us/img707/7886/fp3up.jpg&lt;/a&gt; &lt;a href=&quot;\nhttp://img854.imageshack.us/img854/877/fp4y.jpg&quot; rel=&quot;nofollow&quot; target=&quot;_NEW&quot;&gt;\nhttp://img854.imageshack.us/img854/877/fp4y.jpg&lt;/a&gt; &lt;a href=&quot;\nhttp://img109.imageshack.us/img109/3836/fp5y.jpg&quot; rel=&quot;nofollow&quot; target=&quot;_NEW&quot;&gt;\nhttp://img109.imageshack.us/img109/3836/fp5y.jpg&lt;/a&gt; &lt;a href=&quot;\nhttp://img194.imageshack.us/img194/9831/fp6l.jpg&quot; rel=&quot;nofollow&quot; target=&quot;_NEW&quot;&gt;\nhttp://img194.imageshack.us/img194/9831/fp6l.jpg&lt;/a&gt; &lt;a href=&quot;\nhttp://img198.imageshack.us/img198/299/fp7p.jpg&quot; rel=&quot;nofollow&quot; target=&quot;_NEW&quot;&gt;\nhttp://img198.imageshack.us/img198/299/fp7p.jpg&lt;/a&gt;\n\n\n\n\n\n# The logo/watermark are on these screens only #\n# The encode of the movie is logo/watermark free #\n\n\n\n....::::....           Greetz              ....::::....\n\n\n::::     SDR Release Group     ::::\n\n\n:::::     First  On  Net   HDTVRip   In  Hindi     :::::\n\n\n''Audio Is Properly Sync &amp; Edit - Additional Sound Effects Enhanced''   \n\n           :::::      By  Me     :::::\n\n\n\n....::::....      IF U LIKE MY WORK   ....::::....  \n....::::....           Just  Seed     ....::::.... ","torrent":{"xt":"urn:btih:469a5f0f9099d234bd01672d1fcde60267ae1643","amp;dn":"Foolproof+%282003%29+%7C+HDTVRip+%7C+720p+%7C+Hindi+%7C+Eng+%7C+BHATTI87","amp;tr":["udp%3A%2F%2Ftracker.openbittorrent.com%3A80","udp%3A%2F%2Fopen.demonii.com%3A1337","udp%3A%2F%2Ftracker.coppersurfer.tk%3A6969","udp%3A%2F%2Fexodus.desync.com%3A6969"],"infoHash":"469a5f0f9099d234bd01672d1fcde60267ae1643","infoHashBuffer":{"type":"Buffer","data":[70,154,95,15,144,153,210,52,189,1,103,45,31,205,230,2,103,174,22,67]},"announce":[],"urlList":[]}}