{"title":"Slipknot - 2001 - Iowa","uid":9357614,"size":160383062,"categoryP":"audio","categoryS":"music","magnet":"?xt=urn:btih:4a0f5b849acc1262354de15a98e940d375829bdd&amp;dn=Slipknot+-+2001+-+Iowa&amp;tr=udp%3A%2F%2Ftracker.openbittorrent.com%3A80&amp;tr=udp%3A%2F%2Fopen.demonii.com%3A1337&amp;tr=udp%3A%2F%2Ftracker.coppersurfer.tk%3A6969&amp;tr=udp%3A%2F%2Fexodus.desync.com%3A6969","seeders":3,"leechers":0,"uploader":"iBeholder","files":17,"time":1387243701,"description":"iBeholder - http://www.ibeholder.net/","torrent":{"xt":"urn:btih:4a0f5b849acc1262354de15a98e940d375829bdd","amp;dn":"Slipknot+-+2001+-+Iowa","amp;tr":["udp%3A%2F%2Ftracker.openbittorrent.com%3A80","udp%3A%2F%2Fopen.demonii.com%3A1337","udp%3A%2F%2Ftracker.coppersurfer.tk%3A6969","udp%3A%2F%2Fexodus.desync.com%3A6969"],"infoHash":"4a0f5b849acc1262354de15a98e940d375829bdd","infoHashBuffer":{"type":"Buffer","data":[74,15,91,132,154,204,18,98,53,77,225,90,152,233,64,211,117,130,155,221]},"announce":[],"urlList":[]}}