{"title":"[DDFBusty] Marina Visconti, Chrissy (Distracted By D-Cups / 07.2","uid":8735318,"size":675018512,"categoryP":"porn","categoryS":"movies","magnet":"?xt=urn:btih:56657f0bc80efc6eaf3af8bcaec19bd8173edea5&amp;dn=%5BDDFBusty%5D+Marina+Visconti%2C+Chrissy+%28Distracted+By+D-Cups+%2F+07.2&amp;tr=udp%3A%2F%2Ftracker.openbittorrent.com%3A80&amp;tr=udp%3A%2F%2Fopen.demonii.com%3A1337&amp;tr=udp%3A%2F%2Ftracker.coppersurfer.tk%3A6969&amp;tr=udp%3A%2F%2Fexodus.desync.com%3A6969","seeders":3,"leechers":3,"uploader":"chkm8te","files":2,"time":1374675452,"description":"[DDFBusty] Marina Visconti, Chrissy (Distracted By D-Cups / 07.24.2013 / 17878)\n\nScreens: &lt;a href=&quot;\nhttp://xxxces.com/viewer.php?file=hskwi6oi9sepw1h10esw.jpg&quot; rel=&quot;nofollow&quot; target=&quot;_NEW&quot;&gt;\nhttp://xxxces.com/viewer.php?file=hskwi6oi9sepw1h10esw.jpg&lt;/a&gt;\n &lt;a href=&quot;\nhttp://xxxces.com/viewer.php?file=zi9ik2yd7f5om3v2z8lo.jpg&quot; rel=&quot;nofollow&quot; target=&quot;_NEW&quot;&gt;\nhttp://xxxces.com/viewer.php?file=zi9ik2yd7f5om3v2z8lo.jpg&lt;/a&gt;","torrent":{"xt":"urn:btih:56657f0bc80efc6eaf3af8bcaec19bd8173edea5","amp;dn":"%5BDDFBusty%5D+Marina+Visconti%2C+Chrissy+%28Distracted+By+D-Cups+%2F+07.2","amp;tr":["udp%3A%2F%2Ftracker.openbittorrent.com%3A80","udp%3A%2F%2Fopen.demonii.com%3A1337","udp%3A%2F%2Ftracker.coppersurfer.tk%3A6969","udp%3A%2F%2Fexodus.desync.com%3A6969"],"infoHash":"56657f0bc80efc6eaf3af8bcaec19bd8173edea5","infoHashBuffer":{"type":"Buffer","data":[86,101,127,11,200,14,252,110,175,58,248,188,174,193,155,216,23,62,222,165]},"announce":[],"urlList":[]}}