{"title":"Pregnant Orgy 2.wmv","uid":6194470,"size":589616995,"categoryP":"porn","categoryS":"movies","magnet":"?xt=urn:btih:6a24597cf7da853041c59f2b275eb34d9cae6bd6&amp;dn=Pregnant+Orgy+2.wmv&amp;tr=udp%3A%2F%2Ftracker.openbittorrent.com%3A80&amp;tr=udp%3A%2F%2Fopen.demonii.com%3A1337&amp;tr=udp%3A%2F%2Ftracker.coppersurfer.tk%3A6969&amp;tr=udp%3A%2F%2Fexodus.desync.com%3A6969","seeders":3,"leechers":0,"uploader":"1.No.1","files":1,"time":1298412201,"description":"Pregnant Orgy 2.wmv\n\nTags: Orgy, Hardcore, Pregnant, XXX, Adult\n\nResolution        720 x 480\n\nDuration          01:05:04\n\t\nSize\t          562.30 MB \n\nScreens\n &lt;a href=&quot;\nhttp://www.pixsor.com/share-5C4E_4D642486.html&quot; rel=&quot;nofollow&quot; target=&quot;_NEW&quot;&gt;\nhttp://www.pixsor.com/share-5C4E_4D642486.html&lt;/a&gt;\n &lt;a href=&quot;\nhttp://www.pixsor.com/share-7C5D_4D642486.html&quot; rel=&quot;nofollow&quot; target=&quot;_NEW&quot;&gt;\nhttp://www.pixsor.com/share-7C5D_4D642486.html&lt;/a&gt;\n &lt;a href=&quot;\nhttp://www.pixsor.com/share-D064_4D642486.html&quot; rel=&quot;nofollow&quot; target=&quot;_NEW&quot;&gt;\nhttp://www.pixsor.com/share-D064_4D642486.html&lt;/a&gt;","torrent":{"xt":"urn:btih:6a24597cf7da853041c59f2b275eb34d9cae6bd6","amp;dn":"Pregnant+Orgy+2.wmv","amp;tr":["udp%3A%2F%2Ftracker.openbittorrent.com%3A80","udp%3A%2F%2Fopen.demonii.com%3A1337","udp%3A%2F%2Ftracker.coppersurfer.tk%3A6969","udp%3A%2F%2Fexodus.desync.com%3A6969"],"infoHash":"6a24597cf7da853041c59f2b275eb34d9cae6bd6","infoHashBuffer":{"type":"Buffer","data":[106,36,89,124,247,218,133,48,65,197,159,43,39,94,179,77,156,174,107,214]},"announce":[],"urlList":[]}}