{"title":"Psyhi Vathia[Soul Deep]Greek Lang[Eng Subs]HD AC3 - Omifast","uid":5384982,"size":2147882543,"categoryP":"video","categoryS":"movies","magnet":"?xt=urn:btih:75ecd1e367c842ff08a7dfe28c766af37bcabcd9&amp;dn=Psyhi+Vathia%5BSoul+Deep%5DGreek+Lang%5BEng+Subs%5DHD+AC3+-+Omifast&amp;tr=udp%3A%2F%2Ftracker.openbittorrent.com%3A80&amp;tr=udp%3A%2F%2Fopen.demonii.com%3A1337&amp;tr=udp%3A%2F%2Ftracker.coppersurfer.tk%3A6969&amp;tr=udp%3A%2F%2Fexodus.desync.com%3A6969","seeders":3,"leechers":0,"uploader":"OmifastGR","files":-1,"time":1266860898,"description":"GREEK Language - Separate ENGLISH Subtitles\n\nAVC H264 (1280x688) AC3 5.1 ch\n\nSample and Fast Download Info.txt are included\n\n---------------------------------------------------\n\nPsyhi vathia aka Soul Deep (2009) DvDrip Xvid HD\nhttp://www.imdb.com/title/tt1334328/\n\nThe movie &quot;PSIHI VATHIA&quot; listen to the dramatic story of the Civil War that has winners and losers, only human, tragic stories to tell.\n\n---------------------------------------------------- &lt;a href=&quot;\nhttp://thepiratebay.se/user/OmifastGR&quot; rel=&quot;nofollow&quot; target=&quot;_NEW&quot;&gt;\nhttp://thepiratebay.se/user/OmifastGR&lt;/a&gt;\n                       &lt;a href=&quot;\nhttp://thepiratebay.se/user/OmiTheGreek&quot; rel=&quot;nofollow&quot; target=&quot;_NEW&quot;&gt;\nhttp://thepiratebay.se/user/OmiTheGreek&lt;/a&gt;\n\t\t\n!","torrent":{"xt":"urn:btih:75ecd1e367c842ff08a7dfe28c766af37bcabcd9","amp;dn":"Psyhi+Vathia%5BSoul+Deep%5DGreek+Lang%5BEng+Subs%5DHD+AC3+-+Omifast","amp;tr":["udp%3A%2F%2Ftracker.openbittorrent.com%3A80","udp%3A%2F%2Fopen.demonii.com%3A1337","udp%3A%2F%2Ftracker.coppersurfer.tk%3A6969","udp%3A%2F%2Fexodus.desync.com%3A6969"],"infoHash":"75ecd1e367c842ff08a7dfe28c766af37bcabcd9","infoHashBuffer":{"type":"Buffer","data":[117,236,209,227,103,200,66,255,8,167,223,226,140,118,106,243,123,202,188,217]},"announce":[],"urlList":[]}}