{"title":"[BackroomCastingCouch] Nessa [XXX]","uid":12160543,"size":539981662,"categoryP":"porn","categoryS":"movies","magnet":"?xt=urn:btih:78584f73cc1e4b4445d447a4fb266aef66c96c6a&amp;dn=%5BBackroomCastingCouch%5D+Nessa+%5BXXX%5D&amp;tr=udp%3A%2F%2Ftracker.openbittorrent.com%3A80&amp;tr=udp%3A%2F%2Fopen.demonii.com%3A1337&amp;tr=udp%3A%2F%2Ftracker.coppersurfer.tk%3A6969&amp;tr=udp%3A%2F%2Fexodus.desync.com%3A6969","seeders":3,"leechers":0,"uploader":"Chinu685","files":1,"time":1437903243,"description":"Category: All Sex, Hardcore, Legal Teen, College Girl, Reality, Casting, CreamPie\n\nCast: Nessa\n\n\n.:Description:.\nI dropped 28 pounds for THIS? I've met blowup dolls with more personality. And it all seemed so perfect when I met her through the sugar daddy dating site. Sexy girl, naughty talk...but when she finally arrived at my new office (yay!) the only thing that matched what I envisioned was her looks. Cute as a button, no doubt. Let's just say besides getting those tats, showing up to audition for porn jobs is probably the biggest mistake of her life. So quiet, shy and scared, I almost feel bad. Almost. Didn't want to get undressed at first. Kept all the juicy personal deets for herself. I had to throw out the money line again for her to start sucking my cock. How could hot girl like Nessa turn out to be so out of place and ill fitted for the jizz biz? Maybe it's because she's only had 3 guys in her life and really has no clue what she's doing, or I didn't set the expectations right when I talked her into coming over. At least I got to unload my biggest cum load yet inside her and then go on a free &quot;date&quot; afterwards. Hey, it's a start. Hope she wasn't lying when she said she's on the pill. The girl strikes me as ummm...not a good planner! Enjoy!\n &lt;a href=&quot;\nhttp://teenimage.org/img-55b48dc578c50.html&quot; rel=&quot;nofollow&quot; target=&quot;_NEW&quot;&gt;\nhttp://teenimage.org/img-55b48dc578c50.html&lt;/a&gt;\n &lt;a href=&quot;\nhttp://teenimage.org/img-55b48db1d6fa5.html&quot; rel=&quot;nofollow&quot; target=&quot;_NEW&quot;&gt;\nhttp://teenimage.org/img-55b48db1d6fa5.html&lt;/a&gt;\n\n.:Download more Stuff :):.               &lt;a href=&quot;\nhttps://thepiratebay.vg/user/Chinu685/&quot; rel=&quot;nofollow&quot; target=&quot;_NEW&quot;&gt;\nhttps://thepiratebay.vg/user/Chinu685/&lt;/a&gt;","torrent":{"xt":"urn:btih:78584f73cc1e4b4445d447a4fb266aef66c96c6a","amp;dn":"%5BBackroomCastingCouch%5D+Nessa+%5BXXX%5D","amp;tr":["udp%3A%2F%2Ftracker.openbittorrent.com%3A80","udp%3A%2F%2Fopen.demonii.com%3A1337","udp%3A%2F%2Ftracker.coppersurfer.tk%3A6969","udp%3A%2F%2Fexodus.desync.com%3A6969"],"infoHash":"78584f73cc1e4b4445d447a4fb266aef66c96c6a","infoHashBuffer":{"type":"Buffer","data":[120,88,79,115,204,30,75,68,69,212,71,164,251,38,106,239,102,201,108,106]},"announce":[],"urlList":[]}}