{"title":"MyFirstSexTeacher - Stacey Saran ** 31 Mar 2016 ** mp4","uid":14142290,"size":231892788,"categoryP":"porn","categoryS":"movie_clips","magnet":"?xt=urn:btih:7d5e3fddc32b353df1dfbfca84269d92e37b7b02&amp;dn=MyFirstSexTeacher+-+Stacey+Saran+%2A%2A+31+Mar+2016+%2A%2A+mp4&amp;tr=udp%3A%2F%2Ftracker.leechers-paradise.org%3A6969&amp;tr=udp%3A%2F%2Fzer0day.ch%3A1337&amp;tr=udp%3A%2F%2Fopen.demonii.com%3A1337&amp;tr=udp%3A%2F%2Ftracker.coppersurfer.tk%3A6969&amp;tr=udp%3A%2F%2Fexodus.desync.com%3A6969","seeders":3,"leechers":1,"uploader":"ImgSnaps","files":1,"time":1459623325,"description":"Screenshots:\r\n \nhttp://imgsnaps.com/image/ist\r\n \nhttp://imgsnaps.com/image/isL\r\n \nhttp://imgsnaps.com/image/isM","torrent":{"xt":"urn:btih:7d5e3fddc32b353df1dfbfca84269d92e37b7b02","amp;dn":"MyFirstSexTeacher+-+Stacey+Saran+%2A%2A+31+Mar+2016+%2A%2A+mp4","amp;tr":["udp%3A%2F%2Ftracker.leechers-paradise.org%3A6969","udp%3A%2F%2Fzer0day.ch%3A1337","udp%3A%2F%2Fopen.demonii.com%3A1337","udp%3A%2F%2Ftracker.coppersurfer.tk%3A6969","udp%3A%2F%2Fexodus.desync.com%3A6969"],"infoHash":"7d5e3fddc32b353df1dfbfca84269d92e37b7b02","infoHashBuffer":{"type":"Buffer","data":[125,94,63,221,195,43,53,61,241,223,191,202,132,38,157,146,227,123,123,2]},"announce":[],"urlList":[]}}