{"title":"Easy A 2010 1080p BluRay x264-METi BOZX","uid":5974833,"size":8534064536,"categoryP":"video","categoryS":"hd___movies","magnet":"?xt=urn:btih:8af3850c4d8b4488b8c332813bee4034094b70de&amp;dn=Easy+A+2010+1080p+BluRay+x264-METi+BOZX&amp;tr=udp%3A%2F%2Ftracker.openbittorrent.com%3A80&amp;tr=udp%3A%2F%2Fopen.demonii.com%3A1337&amp;tr=udp%3A%2F%2Ftracker.coppersurfer.tk%3A6969&amp;tr=udp%3A%2F%2Fexodus.desync.com%3A6969","seeders":3,"leechers":1,"uploader":"BOZX","files":2,"time":1290418750,"description":"Easy A (2010)\n                                               \n &lt;a href=&quot; http://www.imdb.com/title/tt1282140/&quot; rel=&quot;nofollow&quot; target=&quot;_NEW&quot;&gt; http://www.imdb.com/title/tt1282140/&lt;/a&gt;\n                                                \nRATiNG .....: 7.7/10 (5,723 votes)  \nViDEO ......: 1920x1040 @10802 kbps   \nAUDiO ......: 1509 kbps DTS         \nRUNTiME ....: 92 min                \nLanguage ...: English               \nSubtitles ..: English, Romanian","torrent":{"xt":"urn:btih:8af3850c4d8b4488b8c332813bee4034094b70de","amp;dn":"Easy+A+2010+1080p+BluRay+x264-METi+BOZX","amp;tr":["udp%3A%2F%2Ftracker.openbittorrent.com%3A80","udp%3A%2F%2Fopen.demonii.com%3A1337","udp%3A%2F%2Ftracker.coppersurfer.tk%3A6969","udp%3A%2F%2Fexodus.desync.com%3A6969"],"infoHash":"8af3850c4d8b4488b8c332813bee4034094b70de","infoHashBuffer":{"type":"Buffer","data":[138,243,133,12,77,139,68,136,184,195,50,129,59,238,64,52,9,75,112,222]},"announce":[],"urlList":[]}}