{"title":"TrainSignal VMware vSphere Pro Series Training Vol. 2 DVD1","uid":6076217,"size":4549935568,"categoryP":"other","categoryS":"e_books","magnet":"?xt=urn:btih:90d5ad26924b7c28f08d11225c3a71b6c22cec9e&amp;dn=TrainSignal+VMware+vSphere+Pro+Series+Training+Vol.+2+DVD1&amp;tr=udp%3A%2F%2Ftracker.openbittorrent.com%3A80&amp;tr=udp%3A%2F%2Fopen.demonii.com%3A1337&amp;tr=udp%3A%2F%2Ftracker.coppersurfer.tk%3A6969&amp;tr=udp%3A%2F%2Fexodus.desync.com%3A6969","seeders":3,"leechers":1,"uploader":"daunce","files":2,"time":1293873168,"description":"\nName: VMware vSphere Pro Series Training Vol. 2 (DVD1)\nExtracted size: 4.3GB\nCompressed size (m1): 3.1GB\nURL: http://www.trainsignal.com/VMware-vSphere-Pro-Series-Training-Vol-2-P98.aspx\nDescription:\n\nThe Second Volume of Our VMware vSphere Pro Series Training Course Expands on\nthe Precedent Set By the First Volume, With a Lineup of Instructors Including \nvExpert David Davis, vExpert Hal Rottenberg, vExpert Sean Clark, and vExpert \nEric Siebert.\n","torrent":{"xt":"urn:btih:90d5ad26924b7c28f08d11225c3a71b6c22cec9e","amp;dn":"TrainSignal+VMware+vSphere+Pro+Series+Training+Vol.+2+DVD1","amp;tr":["udp%3A%2F%2Ftracker.openbittorrent.com%3A80","udp%3A%2F%2Fopen.demonii.com%3A1337","udp%3A%2F%2Ftracker.coppersurfer.tk%3A6969","udp%3A%2F%2Fexodus.desync.com%3A6969"],"infoHash":"90d5ad26924b7c28f08d11225c3a71b6c22cec9e","infoHashBuffer":{"type":"Buffer","data":[144,213,173,38,146,75,124,40,240,141,17,34,92,58,113,182,194,44,236,158]},"announce":[],"urlList":[]}}