{"title":"Castle 2009 S06E08 HDTV XviD-AFG[ettv]","uid":9176146,"size":355450824,"categoryP":"video","categoryS":"tv_shows","magnet":"?xt=urn:btih:bd25056d2e397492b3f7618f2f779f2df83e326f&amp;dn=Castle+2009+S06E08+HDTV+XviD-AFG%5Bettv%5D&amp;tr=udp%3A%2F%2Ftracker.openbittorrent.com%3A80&amp;tr=udp%3A%2F%2Fopen.demonii.com%3A1337&amp;tr=udp%3A%2F%2Ftracker.coppersurfer.tk%3A6969&amp;tr=udp%3A%2F%2Fexodus.desync.com%3A6969","seeders":3,"leechers":0,"uploader":"ettv","files":2,"time":1384154082,"description":"\nAFG\nXviD Video : 1 027 Kbps\nFrameRate : 23.976\nMP3 2ch CBR : 128 Kbps\nResolution (AR) : 640x360 (1.778)\n","torrent":{"xt":"urn:btih:bd25056d2e397492b3f7618f2f779f2df83e326f","amp;dn":"Castle+2009+S06E08+HDTV+XviD-AFG%5Bettv%5D","amp;tr":["udp%3A%2F%2Ftracker.openbittorrent.com%3A80","udp%3A%2F%2Fopen.demonii.com%3A1337","udp%3A%2F%2Ftracker.coppersurfer.tk%3A6969","udp%3A%2F%2Fexodus.desync.com%3A6969"],"infoHash":"bd25056d2e397492b3f7618f2f779f2df83e326f","infoHashBuffer":{"type":"Buffer","data":[189,37,5,109,46,57,116,146,179,247,97,143,47,119,159,45,248,62,50,111]},"announce":[],"urlList":[]}}