{"title":"Color Climax 15-XXX-MAG-SHAREGO","uid":4404280,"size":22246390,"categoryP":"porn","categoryS":"other","magnet":"?xt=urn:btih:c3d8a62626966ba6fd12883c8c48f1e02a1a599e&amp;dn=Color+Climax+15-XXX-MAG-SHAREGO&amp;tr=udp%3A%2F%2Ftracker.openbittorrent.com%3A80&amp;tr=udp%3A%2F%2Fopen.demonii.com%3A1337&amp;tr=udp%3A%2F%2Ftracker.coppersurfer.tk%3A6969&amp;tr=udp%3A%2F%2Fexodus.desync.com%3A6969","seeders":3,"leechers":0,"uploader":"dodgerblue","files":5,"time":1221861511,"description":"Color Climax 15-XXX-MAG-SHAREGO\nFORMAT PDF 21.2 MB\n[IMG]http://www.tinypic.ws/files/cveo1q0297rxiaa1009q.jpg[/IMG]\n[img]http://images1.filecloud.com/607500/Appriciation.gif[/img]\n","torrent":{"xt":"urn:btih:c3d8a62626966ba6fd12883c8c48f1e02a1a599e","amp;dn":"Color+Climax+15-XXX-MAG-SHAREGO","amp;tr":["udp%3A%2F%2Ftracker.openbittorrent.com%3A80","udp%3A%2F%2Fopen.demonii.com%3A1337","udp%3A%2F%2Ftracker.coppersurfer.tk%3A6969","udp%3A%2F%2Fexodus.desync.com%3A6969"],"infoHash":"c3d8a62626966ba6fd12883c8c48f1e02a1a599e","infoHashBuffer":{"type":"Buffer","data":[195,216,166,38,38,150,107,166,253,18,136,60,140,72,241,224,42,26,89,158]},"announce":[],"urlList":[]}}