{"title":"Cuban Music + Vol. 5 of 12 : RubÃƒÂ©n GonzÃƒÂ¡lez, Jaime Guardia, Gy","uid":5553497,"size":1013282919,"categoryP":"audio","categoryS":"other","magnet":"?xt=urn:btih:c5968d84995d1ca0a36ecb3cb90b0895069baf70&amp;dn=Cuban+Music+%2B+Vol.+5+of+12+%3A+Rub%C3%83%C2%A9n+Gonz%C3%83%C2%A1lez%2C+Jaime+Guardia%2C+Gy&amp;tr=udp%3A%2F%2Ftracker.openbittorrent.com%3A80&amp;tr=udp%3A%2F%2Fopen.demonii.com%3A1337&amp;tr=udp%3A%2F%2Ftracker.coppersurfer.tk%3A6969&amp;tr=udp%3A%2F%2Fexodus.desync.com%3A6969","seeders":3,"leechers":0,"uploader":"rubusdemonoid","files":-1,"time":1273610454,"description":"Please help to seed this torrent when you are completed as my ISP has a monthly limit that I always max out on since I have over 50 torrents that I seed for you all. My ISP is going to terminate my service if I max out my monthly limit, so I just can't continue to seed all by myself so often. PLEASE help to seed. Thank you.  :)\n\n\n\nI wanted to share the Cuban music I've collected over the past few years, and some of it is quite rare. All files have proper ID3v1 and ID3v2 tags and include the CD cover art. No guarantees on perfect spelling, especially with capitalization or special characters (e.g. ÃƒÂ¡, ÃƒÂ©, ÃƒÂ±, etc.).\n\nMost are not available online already, and the few that are already posted are in a different format. If you want a higher bit rate or format, the original CD's can be purchased online. Where I purchased most of mine was at &lt;a href=&quot; http://www.timbuktunes.com.&quot; rel=&quot;nofollow&quot; target=&quot;_NEW&quot;&gt; http://www.timbuktunes.com.&lt;/a&gt; They are a GREAT store and they will ship anywhere.\n\nThe collection is quite large, so I will be uploading them in 12 separate torrents. The majority are Cuban-related, but there are some other Latin-based selections from Spain, Brazil, Argentina, Peru, Colombia, Panama and Puerto Rico. I hope you will enjoy them as much as I do.\n\n\n\nCuba + 05 of 12\n\nRubÃƒÂ©n GonzÃƒÂ¡lez\n1997 - Introducing... RubÃƒÂ©n GonzÃƒÂ¡lez\n &lt;a href=&quot; http://www.allmusic.com/cg/amg.dll?p=amg&amp;sql=10:h9fexqljldje&quot; rel=&quot;nofollow&quot; target=&quot;_NEW&quot;&gt; http://www.allmusic.com/cg/amg.dll?p=amg&amp;sql=10:h9fexqljldje&lt;/a&gt;\n\n2000 - Chanchullo\n &lt;a href=&quot; http://www.allmusic.com/cg/amg.dll?p=amg&amp;sql=10:djfoxqukldde&quot; rel=&quot;nofollow&quot; target=&quot;_NEW&quot;&gt; http://www.allmusic.com/cg/amg.dll?p=amg&amp;sql=10:djfoxqukldde&lt;/a&gt;\n\n\nJaime Guardia\n1994 - Y Su Charango\n \n\n\nGypsy Passion - New Flamenco - 1997\n &lt;a href=&quot; http://www.allmusic.com/cg/amg.dll?p=amg&amp;sql=10:gxfqxquhldfe&quot; rel=&quot;nofollow&quot; target=&quot;_NEW&quot;&gt; http://www.allmusic.com/cg/amg.dll?p=amg&amp;sql=10:gxfqxquhldfe&lt;/a&gt;\n\n\nGypsy Soul - New Flamenco - 1998\n &lt;a href=&quot; http://www.allmusic.com/cg/amg.dll?p=amg&amp;sql=10:dxfixqqjldde&quot; rel=&quot;nofollow&quot; target=&quot;_NEW&quot;&gt; http://www.allmusic.com/cg/amg.dll?p=amg&amp;sql=10:dxfixqqjldde&lt;/a&gt;\n\n\nHavana-Lounge - CafÃƒÂ© Ambient - 2001\n &lt;a href=&quot; http://www.allmusic.com/cg/amg.dll?p=amg&amp;sql=10:kvfoxqy0ldae&quot; rel=&quot;nofollow&quot; target=&quot;_NEW&quot;&gt; http://www.allmusic.com/cg/amg.dll?p=amg&amp;sql=10:kvfoxqy0ldae&lt;/a&gt;\n\n\nLa Cuba Mia - 2002\n &lt;a href=&quot; http://www.allmusic.com/cg/amg.dll?p=amg&amp;sql=10:fjfrxql0ldae&quot; rel=&quot;nofollow&quot; target=&quot;_NEW&quot;&gt; http://www.allmusic.com/cg/amg.dll?p=amg&amp;sql=10:fjfrxql0ldae&lt;/a&gt;\n\n\nOttmar Liebert\n1990 - Nouveau Flamenco\n &lt;a href=&quot; http://www.allmusic.com/cg/amg.dll?p=amg&amp;sql=10:3nfwxqw5ldke&quot; rel=&quot;nofollow&quot; target=&quot;_NEW&quot;&gt; http://www.allmusic.com/cg/amg.dll?p=amg&amp;sql=10:3nfwxqw5ldke&lt;/a&gt;\n\n1991 - Borrasca\n &lt;a href=&quot; http://www.allmusic.com/cg/amg.dll?p=amg&amp;sql=10:wpftxqwgld0e&quot; rel=&quot;nofollow&quot; target=&quot;_NEW&quot;&gt; http://www.allmusic.com/cg/amg.dll?p=amg&amp;sql=10:wpftxqwgld0e&lt;/a&gt;\n\n1991 - Poets &amp; Angels\n &lt;a href=&quot; http://www.allmusic.com/cg/amg.dll?p=amg&amp;sql=10:kpftxqwgld0e&quot; rel=&quot;nofollow&quot; target=&quot;_NEW&quot;&gt; http://www.allmusic.com/cg/amg.dll?p=amg&amp;sql=10:kpftxqwgld0e&lt;/a&gt;\n\n1992 - Solo Para Ti\n &lt;a href=&quot; http://www.allmusic.com/cg/amg.dll?p=amg&amp;sql=10:3pfyxqwgld0e&quot; rel=&quot;nofollow&quot; target=&quot;_NEW&quot;&gt; http://www.allmusic.com/cg/amg.dll?p=amg&amp;sql=10:3pfyxqwgld0e&lt;/a&gt;\n\n1997 - Leaning into the Night - Inclinado en la Noche\n &lt;a href=&quot; http://www.allmusic.com/cg/amg.dll?p=amg&amp;sql=10:k9fexqqjld0e&quot; rel=&quot;nofollow&quot; target=&quot;_NEW&quot;&gt; http://www.allmusic.com/cg/amg.dll?p=amg&amp;sql=10:k9fexqqjld0e&lt;/a&gt;\n\n1998 - Rumba Collection 1992-1997\n &lt;a href=&quot; http://www.allmusic.com/cg/amg.dll?p=amg&amp;sql=10:wcfqxqqjldte&quot; rel=&quot;nofollow&quot; target=&quot;_NEW&quot;&gt; http://www.allmusic.com/cg/amg.dll?p=amg&amp;sql=10:wcfqxqqjldte&lt;/a&gt;\n\n1999 - Innamorare - Summer Flamenco\n &lt;a href=&quot; http://www.allmusic.com/cg/amg.dll?p=amg&amp;sql=10:k9fpxqrkldfe&quot; rel=&quot;nofollow&quot; target=&quot;_NEW&quot;&gt; http://www.allmusic.com/cg/amg.dll?p=amg&amp;sql=10:k9fpxqrkldfe&lt;/a&gt;\n\n2000 - Nouveau Flamenco - 1990-2000 Special Tenth Anniversary Edition\n &lt;a href=&quot; http://www.allmusic.com/cg/amg.dll?p=amg&amp;sql=10:wvfqxqtkldte&quot; rel=&quot;nofollow&quot; target=&quot;_NEW&quot;&gt; http://www.allmusic.com/cg/amg.dll?p=amg&amp;sql=10:wvfqxqtkldte&lt;/a&gt;\n\n2001 - Little Wing\n &lt;a href=&quot; http://www.allmusic.com/cg/amg.dll?p=amg&amp;sql=10:dzfwxqw0ldhe&quot; rel=&quot;nofollow&quot; target=&quot;_NEW&quot;&gt; http://www.allmusic.com/cg/amg.dll?p=amg&amp;sql=10:dzfwxqw0ldhe&lt;/a&gt;\n\n2002 - The Santa Fe Sessions\n &lt;a href=&quot; http://www.allmusic.com/cg/amg.dll?p=amg&amp;sql=10:hpfoxqealdse&quot; rel=&quot;nofollow&quot; target=&quot;_NEW&quot;&gt; http://www.allmusic.com/cg/amg.dll?p=amg&amp;sql=10:hpfoxqealdse&lt;/a&gt;\n\n2004 - La Semana\n &lt;a href=&quot; http://www.allmusic.com/cg/amg.dll?p=amg&amp;sql=10:gifexqesldse&quot; rel=&quot;nofollow&quot; target=&quot;_NEW&quot;&gt; http://www.allmusic.com/cg/amg.dll?p=amg&amp;sql=10:gifexqesldse&lt;/a&gt;\n\nVarious Bonus\n\n\n\n\n\n\n\nMore of my music &amp; movie downloads that you may find of interest are located here:\n &lt;a href=&quot; http://thepiratebay.se/user/rubusdemonoid/&quot; rel=&quot;nofollow&quot; target=&quot;_NEW&quot;&gt; http://thepiratebay.se/user/rubusdemonoid/&lt;/a&gt;\n\n","torrent":{"xt":"urn:btih:c5968d84995d1ca0a36ecb3cb90b0895069baf70","amp;dn":"Cuban+Music+%2B+Vol.+5+of+12+%3A+Rub%C3%83%C2%A9n+Gonz%C3%83%C2%A1lez%2C+Jaime+Guardia%2C+Gy","amp;tr":["udp%3A%2F%2Ftracker.openbittorrent.com%3A80","udp%3A%2F%2Fopen.demonii.com%3A1337","udp%3A%2F%2Ftracker.coppersurfer.tk%3A6969","udp%3A%2F%2Fexodus.desync.com%3A6969"],"infoHash":"c5968d84995d1ca0a36ecb3cb90b0895069baf70","infoHashBuffer":{"type":"Buffer","data":[197,150,141,132,153,93,28,160,163,110,203,60,185,11,8,149,6,155,175,112]},"announce":[],"urlList":[]}}