{"title":"The Block NZ S05E38 480p.HDTV.x264-RMTeam.mkv","uid":15465040,"size":275760192,"categoryP":"video","categoryS":"tv_shows","magnet":"?xt=urn:btih:caa846a419feb6c3c7aead4eeea344aeaf9aa7bb&amp;dn=The+Block+NZ+S05E38+480p.HDTV.x264-RMTeam.mkv&amp;tr=udp%3A%2F%2Ftracker.leechers-paradise.org%3A6969&amp;tr=udp%3A%2F%2Fzer0day.ch%3A1337&amp;tr=udp%3A%2F%2Fopen.demonii.com%3A1337&amp;tr=udp%3A%2F%2Ftracker.coppersurfer.tk%3A6969&amp;tr=udp%3A%2F%2Fexodus.desync.com%3A6969","seeders":3,"leechers":2,"uploader":"TlanImass","files":1,"time":1470089538,"description":"The Block New Zealand - Season 5, Episode 38\r\n\r\n\r\n\r\n\r\nThe final push to complete The Block houses begins, and Mother Nature opens the floodgates for delays. Then, broken banks lead to broken spirits as one team completely blows the budget.\r\n\r\n\r\n\r\n\r\nOriginal Air Date: 01-Aug-2016","torrent":{"xt":"urn:btih:caa846a419feb6c3c7aead4eeea344aeaf9aa7bb","amp;dn":"The+Block+NZ+S05E38+480p.HDTV.x264-RMTeam.mkv","amp;tr":["udp%3A%2F%2Ftracker.leechers-paradise.org%3A6969","udp%3A%2F%2Fzer0day.ch%3A1337","udp%3A%2F%2Fopen.demonii.com%3A1337","udp%3A%2F%2Ftracker.coppersurfer.tk%3A6969","udp%3A%2F%2Fexodus.desync.com%3A6969"],"infoHash":"caa846a419feb6c3c7aead4eeea344aeaf9aa7bb","infoHashBuffer":{"type":"Buffer","data":[202,168,70,164,25,254,182,195,199,174,173,78,238,163,68,174,175,154,167,187]},"announce":[],"urlList":[]}}