{"title":"Indian Girl Picked Up From A Party And Fucked By A White Guy","uid":9213777,"size":183924602,"categoryP":"porn","categoryS":"movie_clips","magnet":"?xt=urn:btih:d87f366896e51c6dbca5ad2d9af0e522adcd4695&amp;dn=Indian+Girl+Picked+Up+From+A+Party+And+Fucked+By+A+White+Guy&amp;tr=udp%3A%2F%2Ftracker.openbittorrent.com%3A80&amp;tr=udp%3A%2F%2Fopen.demonii.com%3A1337&amp;tr=udp%3A%2F%2Ftracker.coppersurfer.tk%3A6969&amp;tr=udp%3A%2F%2Fexodus.desync.com%3A6969","seeders":3,"leechers":0,"uploader":"nwpornup","files":-1,"time":1384831262,"description":"Screens: &lt;a href=&quot;\nhttp://bayimg.com/BacLLaAfi&quot; rel=&quot;nofollow&quot; target=&quot;_NEW&quot;&gt;\nhttp://bayimg.com/BacLLaAfi&lt;/a&gt;\nor &lt;a href=&quot;\nhttp://imgbits.com/share.php?id=4F0E_528AC95C&quot; rel=&quot;nofollow&quot; target=&quot;_NEW&quot;&gt;\nhttp://imgbits.com/share.php?id=4F0E_528AC95C&lt;/a&gt;","torrent":{"xt":"urn:btih:d87f366896e51c6dbca5ad2d9af0e522adcd4695","amp;dn":"Indian+Girl+Picked+Up+From+A+Party+And+Fucked+By+A+White+Guy","amp;tr":["udp%3A%2F%2Ftracker.openbittorrent.com%3A80","udp%3A%2F%2Fopen.demonii.com%3A1337","udp%3A%2F%2Ftracker.coppersurfer.tk%3A6969","udp%3A%2F%2Fexodus.desync.com%3A6969"],"infoHash":"d87f366896e51c6dbca5ad2d9af0e522adcd4695","infoHashBuffer":{"type":"Buffer","data":[216,127,54,104,150,229,28,109,188,165,173,45,154,240,229,34,173,205,70,149]},"announce":[],"urlList":[]}}