{"title":"Within Temptation And The Metropole Orchestra - Black Symphony (","uid":4403742,"size":196807999,"categoryP":"audio","categoryS":"music","magnet":"?xt=urn:btih:d98d0475af58968213f86da0cbeb4eb8788349b4&amp;dn=Within+Temptation+And+The+Metropole+Orchestra+-+Black+Symphony+%28&amp;tr=udp%3A%2F%2Ftracker.openbittorrent.com%3A80&amp;tr=udp%3A%2F%2Fopen.demonii.com%3A1337&amp;tr=udp%3A%2F%2Ftracker.coppersurfer.tk%3A6969&amp;tr=udp%3A%2F%2Fexodus.desync.com%3A6969","seeders":3,"leechers":0,"uploader":"DivXNL-Team","files":26,"time":1221839854,"description":"Within Temptation And The Metropole Orchestra\nBlack Symphony (2008)\n\nGenre: Rock &amp; Metal\n\n\nCD1:\n01. Ouverture (7:43)\n02. Jillian (I&amp;#039;d Give My Heart) (4:39)\n03. The Howling (6:30)\n04. Stand My Ground (4:32)\n05. The Cross (4:58)\n06. What Have You Done (Featuring Keith Caputo) (5:21)\n07. Hand Of Sorrow (5:40)\n08. The Heart Of Everything (5:47)\n09. Forgiven (4:52)\n10. Somewhere (Featuring Anneke Van Giersbergen) (4:24)\n11. The Swan Song (4:00)\n12. Memories (4:03)\n\nCD2:\n01. Our Solemn Hour (5:22)\n02. The Other Half (Of Me) (Featuring George Oosthoek) (5:03)\n03. Frozen (4:31)\n04. The Promise (8:14)\n05. Angels (4:01)\n06. Mother Earth (5:59)\n07. The Thruth Beneath The Rose (7:22)\n08. Deceiver Of Fools (7:38)\n09. All I Need (4:54)\n10. Ice Queen (7:15)\n\n\nDivXNL-Team Means; Hardburned Dutch Subbed\n &lt;a href=&quot;\nhttp://gratisforums.com/divxnlteam/index.php&quot; rel=&quot;nofollow&quot; target=&quot;_NEW&quot;&gt;\nhttp://gratisforums.com/divxnlteam/index.php&lt;/a&gt;   DivXNL, De NL Films Site\n","torrent":{"xt":"urn:btih:d98d0475af58968213f86da0cbeb4eb8788349b4","amp;dn":"Within+Temptation+And+The+Metropole+Orchestra+-+Black+Symphony+%28","amp;tr":["udp%3A%2F%2Ftracker.openbittorrent.com%3A80","udp%3A%2F%2Fopen.demonii.com%3A1337","udp%3A%2F%2Ftracker.coppersurfer.tk%3A6969","udp%3A%2F%2Fexodus.desync.com%3A6969"],"infoHash":"d98d0475af58968213f86da0cbeb4eb8788349b4","infoHashBuffer":{"type":"Buffer","data":[217,141,4,117,175,88,150,130,19,248,109,160,203,235,78,184,120,131,73,180]},"announce":[],"urlList":[]}}