{"title":"Here with Me (The Archer Brothers #1) by Heidi McLaughlin","uid":11347749,"size":1922479,"categoryP":"other","categoryS":"e_books","magnet":"?xt=urn:btih:dd6fb3cf770317423f3106b83a79f70145a7d243&amp;dn=Here+with+Me+%28The+Archer+Brothers+%231%29+by+Heidi+McLaughlin&amp;tr=udp%3A%2F%2Ftracker.openbittorrent.com%3A80&amp;tr=udp%3A%2F%2Fopen.demonii.com%3A1337&amp;tr=udp%3A%2F%2Ftracker.coppersurfer.tk%3A6969&amp;tr=udp%3A%2F%2Fexodus.desync.com%3A6969","seeders":3,"leechers":0,"uploader":"PhriedPhish","files":4,"time":1414877738,"description":"[b]Published: October 23rd 2014 [/b]\n\nRyley Clarke has grown up with the military in her blood, with both parents serving their country. Ryley knows the risks of being married to the military. But when the unthinkable happens, and her future husband is killed in action, Ryley can barely survive... until Evan's twin brother, Nate, helps her pick up the pieces.\n\nAfter serving on a special mission with the military for six years, Evan Archer returns home to find the unthinkable - the love of his life, Ryley Clarke - engaged to his brother, Nate. With Nate on deployment, Evan needs to figure out what happened in his absence, and more importantly, how to win Ryley back from the man he once considered his best friend, but now thinks of as his rival","torrent":{"xt":"urn:btih:dd6fb3cf770317423f3106b83a79f70145a7d243","amp;dn":"Here+with+Me+%28The+Archer+Brothers+%231%29+by+Heidi+McLaughlin","amp;tr":["udp%3A%2F%2Ftracker.openbittorrent.com%3A80","udp%3A%2F%2Fopen.demonii.com%3A1337","udp%3A%2F%2Ftracker.coppersurfer.tk%3A6969","udp%3A%2F%2Fexodus.desync.com%3A6969"],"infoHash":"dd6fb3cf770317423f3106b83a79f70145a7d243","infoHashBuffer":{"type":"Buffer","data":[221,111,179,207,119,3,23,66,63,49,6,184,58,121,247,1,69,167,210,67]},"announce":[],"urlList":[]}}