{"title":"Cassius - I Love You So (Skream Remix) [256KBPS][.EARL.]","uid":6739225,"size":9294103,"categoryP":"audio","categoryS":"music","magnet":"?xt=urn:btih:e143069642ada943085bb60f16916de5d5e7dced&amp;dn=Cassius+-+I+Love+You+So+%28Skream+Remix%29+%5B256KBPS%5D%5B.EARL.%5D&amp;tr=udp%3A%2F%2Ftracker.openbittorrent.com%3A80&amp;tr=udp%3A%2F%2Fopen.demonii.com%3A1337&amp;tr=udp%3A%2F%2Ftracker.coppersurfer.tk%3A6969&amp;tr=udp%3A%2F%2Fexodus.desync.com%3A6969","seeders":3,"leechers":0,"uploader":".EARL.","files":1,"time":1318431039,"description":"Upload of a quality tune I cant find anywhere on the internet\n\nPlease seed &amp; enjoy\n\nMediaInfo:\nFormat                                   : MPEG Audio\nFile size                                : 8.86 MiB\nDuration                                 : 4mn 49s\nOverall bit rate                         : 256 Kbps\nTrack name                               : I Love You So (Skream Remix)\nPerformer                                : Cassius\nEncoded date                             : UTC 2011-01- 1 14:16:33\nWriting library                          : LAME3.98.4\nEncoding settings                        : Lavf52.87.1\nmajor_brand                              : mp42\nminor_version                            : 0\ncompatible_brands                        : isommp42\n\nAudio\nFormat                                   : MPEG Audio\nFormat version                           : Version 1\nFormat profile                           : Layer 3\nMode                                     : Joint stereo\nDuration                                 : 4mn 50s\nBit rate mode                            : Constant\nBit rate                                 : 256 Kbps\nChannel(s)                               : 2 channels\nSampling rate                            : 44.1 KHz\nCompression mode                         : Lossy\nStream size                              : 8.85 MiB (100%)\nWriting library                          : LAME3.98.4\n\nCheers\n.EARL.","torrent":{"xt":"urn:btih:e143069642ada943085bb60f16916de5d5e7dced","amp;dn":"Cassius+-+I+Love+You+So+%28Skream+Remix%29+%5B256KBPS%5D%5B.EARL.%5D","amp;tr":["udp%3A%2F%2Ftracker.openbittorrent.com%3A80","udp%3A%2F%2Fopen.demonii.com%3A1337","udp%3A%2F%2Ftracker.coppersurfer.tk%3A6969","udp%3A%2F%2Fexodus.desync.com%3A6969"],"infoHash":"e143069642ada943085bb60f16916de5d5e7dced","infoHashBuffer":{"type":"Buffer","data":[225,67,6,150,66,173,169,67,8,91,182,15,22,145,109,229,213,231,220,237]},"announce":[],"urlList":[]}}