{"title":"Heat (1995) Fuego Contra Fuego DVDR NTSC subs Eng Spa Por","uid":6935605,"size":4687099904,"categoryP":"video","categoryS":"movies_dvdr","magnet":"?xt=urn:btih:e7186a82c9d03a7673783cea9a7316a07f9632ac&amp;dn=Heat+%281995%29+Fuego+Contra+Fuego+DVDR+NTSC+subs+Eng+Spa+Por&amp;tr=udp%3A%2F%2Ftracker.openbittorrent.com%3A80&amp;tr=udp%3A%2F%2Fopen.demonii.com%3A1337&amp;tr=udp%3A%2F%2Ftracker.coppersurfer.tk%3A6969&amp;tr=udp%3A%2F%2Fexodus.desync.com%3A6969","seeders":3,"leechers":0,"uploader":"JamesPY","files":-1,"time":1325813628,"description":"Heat (1995) Fuego Contra Fuego\n\nStars:......Al Pacino, Robert De Niro, Val Kilmer\nDirector:...Michael Mann\nGenre:......Action Crime Drama\nLanguage:...English Portuguese\nSubtitles:..English Portuguese Spanish\nRuntime.....170 min\nIncludes director's comments\n\nAwesome movie! Estupenda pelicula!\nKeep seeding. Mantener semillas","torrent":{"xt":"urn:btih:e7186a82c9d03a7673783cea9a7316a07f9632ac","amp;dn":"Heat+%281995%29+Fuego+Contra+Fuego+DVDR+NTSC+subs+Eng+Spa+Por","amp;tr":["udp%3A%2F%2Ftracker.openbittorrent.com%3A80","udp%3A%2F%2Fopen.demonii.com%3A1337","udp%3A%2F%2Ftracker.coppersurfer.tk%3A6969","udp%3A%2F%2Fexodus.desync.com%3A6969"],"infoHash":"e7186a82c9d03a7673783cea9a7316a07f9632ac","infoHashBuffer":{"type":"Buffer","data":[231,24,106,130,201,208,58,118,115,120,60,234,154,115,22,160,127,150,50,172]},"announce":[],"urlList":[]}}