{"title":"Python Testing Cookbook","uid":6528835,"size":9583473,"categoryP":"other","categoryS":"e_books","magnet":"?xt=urn:btih:f17074bfc02704e9ece9647453965184f75ff922&amp;dn=Python+Testing+Cookbook&amp;tr=udp%3A%2F%2Ftracker.openbittorrent.com%3A80&amp;tr=udp%3A%2F%2Fopen.demonii.com%3A1337&amp;tr=udp%3A%2F%2Ftracker.coppersurfer.tk%3A6969&amp;tr=udp%3A%2F%2Fexodus.desync.com%3A6969","seeders":3,"leechers":0,"uploader":"theLEAK","files":-1,"time":1310251518,"description":"This cookbook is written as a collection of code recipes containing step-by-step directions on how to install or build different types of Python test tools to solve different problems. Each recipe contains explanations of how it works along with answers to common questions and cross references to other relevant recipes. The easy-to-understand recipe names make this a handy test reference book.\n\nPython developers and programmers with a basic understanding of Python and Python testing will find this cookbook beneficial. It will build on that basic knowledge equipping you with the intermediate and advanced skills required to fully utilize the Python testing tools. Broken up into lots of small code recipes, you can read this book at your own pace, whatever your experience. No prior experience of automated testing is required.","torrent":{"xt":"urn:btih:f17074bfc02704e9ece9647453965184f75ff922","amp;dn":"Python+Testing+Cookbook","amp;tr":["udp%3A%2F%2Ftracker.openbittorrent.com%3A80","udp%3A%2F%2Fopen.demonii.com%3A1337","udp%3A%2F%2Ftracker.coppersurfer.tk%3A6969","udp%3A%2F%2Fexodus.desync.com%3A6969"],"infoHash":"f17074bfc02704e9ece9647453965184f75ff922","infoHashBuffer":{"type":"Buffer","data":[241,112,116,191,192,39,4,233,236,233,100,116,83,150,81,132,247,95,249,34]},"announce":[],"urlList":[]}}